rr/__init__.py
rr/inject/__init__.py
rr_inject/__init__.py
rr_inject-0.2.0.dist-info/LICENSE.txt
rr_inject-0.2.0.dist-info/METADATA
rr_inject-0.2.0.dist-info/WHEEL
rr_inject-0.2.0.dist-info/top_level.txt
rr_inject-0.2.0.dist-info/RECORD
