Metadata-Version: 2.1
Name: rr-inject
Version: 0.2.0
Summary: Dependency Injection library for Python using decorators.
Home-page: https://github.com/fredriques/rr-pyinject
Author: Fredrique Samuels
License: MIT
Project-URL: Documentation, https://github.com/fredriques/rr-pyinject?tab=readme-ov-file#readme
Project-URL: Source, https://github.com/fredriques/rr-pyinject
Project-URL: Health, https://github.com/fredriques/rr-pyinject/actions
Platform: UNKNOWN
Classifier: Development Status :: 3 - Alpha
Classifier: Intended Audience :: Developers
Classifier: Programming Language :: Python :: 3.8
Classifier: Programming Language :: Python :: 3.11
Classifier: Topic :: Utilities
Requires-Python: >=3.8,<3.12
